eanoui/__init__.py
eanoui/admin.py
eanoui/apps.py
eanoui/forms.py
eanoui/widgets.py
eanoui-1.1.2.dist-info/LICENSE
eanoui-1.1.2.dist-info/METADATA
eanoui-1.1.2.dist-info/WHEEL
eanoui-1.1.2.dist-info/top_level.txt
eanoui-1.1.2.dist-info/RECORD
