Metadata-Version: 2.1
Name: eanoui
Version: 1.1.2
Summary: django admin theme 后台模板 based on simpleui
Home-page: https://www.eano.com
Author: Hongbin
Author-email: hongbin@eano.com
License: Apache License 2.0
Platform: UNKNOWN
Classifier: Programming Language :: Python :: 3
Classifier: Operating System :: OS Independent
Requires-Dist: django
